MANIFEST.in
README.md
dev.txt
setup.py
shimmers/__init__.py
shimmers/sharepoint_client.py
shimmers/version_info.py
shimmers.egg-info/PKG-INFO
shimmers.egg-info/SOURCES.txt
shimmers.egg-info/dependency_links.txt
shimmers.egg-info/requires.txt
shimmers.egg-info/top_level.txt